Metadata-Version: 2.1
Name: texta-anonymizer
Version: 1.1.2
Summary: texta-anonymizer
Home-page: https://git.texta.ee/texta/texta-anonymizer-python
Author: TEXTA
Author-email: info@texta.ee
License: GPLv3
Platform: UNKNOWN
